insta_api/__init__.py
insta_api/endpoints.py
insta_api/exceptions.py
insta_api/insta_api.py
insta_api/server_errors.py
insta_api/utils.py
insta_api-0.2.4.dist-info/METADATA
insta_api-0.2.4.dist-info/RECORD
insta_api-0.2.4.dist-info/WHEEL
insta_api-0.2.4.dist-info/top_level.txt
