Metadata-Version: 2.1
Name: insta_api
Version: 0.2.4
Summary: Unofficial instagram API
Home-page: https://github.com/orlandodiaz/insta_api
Author: Orlando Diaz
Author-email: orlandodiaz.dev@gmail.com
License: UNKNOWN
Platform: UNKNOWN
Classifier: Programming Language :: Python :: 3
Classifier: License :: OSI Approved :: MIT License
Classifier: Operating System :: OS Independent
